{
  "Email": "الايميل",
  "Password": "كلمة السر",
  "Login": "تسجيل الدخول",
  "Dashboard": "لوحة التحكم",
  "Inventory": "المخزون",
  "Sales": "المبيعات",
  "Purchases": "المشتريات",
  "Stores": "المستودعات",
  "There is no data to show": "لا توجد بيانات للعرض",
  "Add machine part": "إضافة جزْ من ألأله",
  "Search": "بحث",
  "Create new machine part": "إنشاء جزء آلة جديد",
  "Save": "حفظ",
  "Cancel": "إلغاء",
  "Arabic Name": "الاسم بالعربية",
  "English Name": "الاسم بالانجليزية",
  "Add Store": "اضف مستودع",
  "Name": "الاسم",
  "City": "المدينة",
  "Status": "الحالة",
  "Last updated": "اخر تحديث",
  "Location count": "عدد المواقع",
  "Actions": "اجراءات",
  "Active": "فعال",
  "Arabic City Name": "اسم المدينة بالعربية",
  "English City Name": "اسم المدينة بالانجليزية",
  "Countries": "البلدان",
  "Locations": "المواقع",
  "Add Location": "إضافة موقع",
  "Edit": "تعديل",
  "Edit Location": "تعديل الموقع",
  "Brands": "العلامات التجارية",
  "Add Brand": "إضافة علامة تجارية",
  "Add Sub Brand": "إضافة علامة تجارية فرعية",
  "Code": "الكود",
  "Machine Parts": "قطع الآلات",
  "Machine Part": "قطعة الآلة",
  "Edit Machine Part": "تعديل قطعة الآلة",
  "Products": "المنتجات",
  "Is original": "هل هو أصلي",
  "Unit": "الوحدة",
  "Create new Product part": "إنشاء جزء منتج جديد",
  "Product Number": "رقم المنتج",
  "Arabic Description": "الوصف العربي",
  "English Description": "الوصف الإنجليزي",
  "Product Image": "صورة المنتج",
  "Machine Part Image": "صورة قطعة الآلة",
  "Minimum Quantity": "الكمية الدنيا",
  "Is Original": "هل هو أصلي",
  "Sell As Set": "بيع كمجموعة",
  "Sell As Piece": "بيع بالقطعة",
  "Add Alternatives": "إضافة بدائل",
  "Select Product Alternatives": "اختيار بدائل المنتجات",
  "Select Set Products": "اختيار منتجات المجموعة",
  "Quantity": "الكمية",
  "Add Product": "إضافة منتج",
  "Description": "الوصف",
  "Same Items": "المنتجات نفسها",
  "Alternative": "بديل",
  "Stock": "المخزون",
  "Add opening balance": "إضافة رصيد الافتتاح",
  "Brand Code": "الكود",
  "Number": "رقم",
  "Brand": "علامة تجارية",
  "Sub Brand": "علامة تجارية فرعية",
  "Country": "دولة",
  "Save Set": "حفظ المجموعة",
  "Save Alternatives": "حفظ البدائل",
  "Store": "مخزن",
  "Location": "موقع",
  "Product": "المنتج",
  "Core": "الاساسية",
  "": ""
}
